pip_lock/__init__.py
pip_lock/py.typed
pip_lock-2.13.0.dist-info/licenses/LICENSE
pip_lock-2.13.0.dist-info/METADATA
pip_lock-2.13.0.dist-info/WHEEL
pip_lock-2.13.0.dist-info/top_level.txt
pip_lock-2.13.0.dist-info/RECORD
