Metadata-Version: 2.4
Name: pip-lock
Version: 2.13.0
Summary: Check for differences between requirements.txt files and your environment.
Author: Adam Johnson, et al.
Author-email: Aaron Kirkbride <me@adamj.eu>
License-Expression: MIT
Project-URL: Changelog, https://github.com/adamchainz/pip-lock/blob/main/CHANGELOG.rst
Project-URL: Funding, https://adamj.eu/books/
Project-URL: Repository, https://github.com/adamchainz/pip-lock
Keywords: pip,requirements
Classifier: Development Status :: 5 - Production/Stable
Classifier: Intended Audience :: Developers
Classifier: Operating System :: OS Independent
Classifier: Programming Language :: Python
Classifier: Programming Language :: Python :: 3 :: Only
Classifier: Programming Language :: Python :: 3.9
Classifier: Programming Language :: Python :: 3.10
Classifier: Programming Language :: Python :: 3.11
Classifier: Programming Language :: Python :: 3.12
Classifier: Programming Language :: Python :: 3.13
Classifier: Programming Language :: Python :: 3.14
Classifier: Topic :: Utilities
Classifier: Typing :: Typed
Requires-Python: >=3.9
License-File: LICENSE
Dynamic: license-file
